svROS/__init__.py
svROS/__main__.py
svROS/svAnalyzer.py
svROS/svData.py
svROS/svExport.py
svROS/svGrammar.py
svROS/svInfo.py
svROS/svInitGrammar.py
svROS/svLanguage.py
svROS/svLauncherPY.py
svROS/svLauncherXML.py
svROS/svROS.py
svROS/svVisualizer.py
svROS/bin/generator.jar
svROS/bin/numeric.als
svROS/bin/org.alloytools.alloy.dist.jar
svROS/bin/ros_base.als
svROS/bin/sros_base.als
svROS/bin/generator/generator.iml
svROS/bin/generator/org.alloytools.alloy.dist.jar
svROS/bin/generator/pom.xml
svROS/bin/generator/slf4j-api-1.7.5.jar
svROS/bin/generator/slf4j-log4j12-1.7.5.jar
svROS/bin/generator/slf4j-simple-1.6.4.jar
svROS/bin/generator/.idea/.gitignore
svROS/bin/generator/.idea/compiler.xml
svROS/bin/generator/.idea/jarRepositories.xml
svROS/bin/generator/.idea/misc.xml
svROS/bin/generator/.idea/modules.xml
svROS/bin/generator/.idea/vcs.xml
svROS/bin/generator/.idea/workspace.xml
svROS/bin/generator/.idea/artifacts/generator_jar.xml
svROS/bin/generator/.idea/libraries/Maven__org_slf4j_slf4j_api_1_7_5.xml
svROS/bin/generator/.idea/libraries/Maven__org_slf4j_slf4j_simple_1_6_4.xml
svROS/bin/generator/out/artifacts/generator_jar/generator.jar
svROS/bin/generator/src/main/java/Generator.java
svROS/bin/generator/src/main/resources/META-INF/MANIFEST.MF
svROS/bin/generator/target/classes/Generator.class
svROS/bin/generator/target/classes/META-INF/MANIFEST.MF
svROS/schemas/launch.xsd
svROS/schemas/sros/sros.xsd
svROS/schemas/sros/template.xml
svROS/schemas/sros/common/lifecycle_node.xml
svROS/schemas/sros/common/node.xml
svROS/schemas/sros/common/node/logging.xml
svROS/schemas/sros/common/node/parameters.xml
svROS/schemas/sros/common/node/time.xml
svROS/visualizer/README.md
svROS/visualizer/template-network.html
svROS/visualizer/template-obsdet.html
svROS/visualizer/template-security.html
svROS/visualizer/vis-example.png
svROS/visualizer/css/style.css
svROS/visualizer/css/w3.css
svROS/visualizer/js/cytoscape-cose-bilkent.js
svROS/visualizer/js/cytoscape.js
svROS-1.0.1.dist-info/LICENSE
svROS-1.0.1.dist-info/METADATA
svROS-1.0.1.dist-info/WHEEL
svROS-1.0.1.dist-info/entry_points.txt
svROS-1.0.1.dist-info/top_level.txt
svROS-1.0.1.dist-info/zip-safe
svROS-1.0.1.dist-info/RECORD
