Metadata-Version: 2.1
Name: svROS
Version: 1.0.1
Summary: Security Verification in ROS
Home-page: https://github.com/luis1ribeiro/svROS
Author: Luís Ribeiro
Author-email: lmmr@outlook.pt
License: MIT License
Keywords: python sros2 ros2 property-specification model-checking alloy haros
License-File: LICENSE
Requires-Dist: argparse
Requires-Dist: bonsai-code (>=0.6.7)
Requires-Dist: xmlschema
Requires-Dist: hpl-specs
Requires-Dist: lark (<=0.12)
Requires-Dist: networkx
Requires-Dist: simple-term-menu
Requires-Dist: jinja2
